Workbook

Sheet README
A1: The Downtown house, a social hub at Megaro Foumi — financial model
A2: Reconstructed source model for the GBR Consulting business plan (May 2024, draft)
A4: WHAT THIS FILE IS
A5: A working version of the spreadsheet model behind the plan's financial tables (pages 9-11).
A6: It was reverse-engineered from the printed figures: every relationship below reproduces the PDF
A7: to the euro, and the 'Check vs PDF' sheet proves it against all ~230 printed numbers.
A9: HOW TO USE IT
A10: 1. All inputs live on the 'Inputs' sheet in the blue cells; everything else is formulas.
A11: 2. Pick a scenario in Inputs!B4 (Base / Upside / Downside). Base = the plan as published.
A12: Upside and Downside start as illustrative placeholders — overwrite them with your own scenarios.
A13: 3. 'Model' is the P&L (2025-2044); 'Returns' gives net cash flow, NPV and IRR (2024-2044).
A14: 4. 'Check vs PDF' compares the live model to the printed figures. With the Base scenario every
... A38: - This reconstruction is for analysis; it is not GBR Consulting's original file.

Sheet Inputs
A1: Inputs & scenarios — The Downtown house, Megaro Foumi
A2: Edit the blue cells. The model reads the 'Active value' column, driven by the scenario selector below. Base reproduces the May 2024 GBR plan; Upside/Downside are illustrative placeholders — set them to whatever scenarios you want to test.
A4: Active scenario | B4: Base
A6: Driver | B6: Unit | C6: Base | D6: Upside | E6: Downside | F6: Active value
A7: ACCOMMODATION
A8: Number of rooms | B8: rooms | C8: 5 | D8: 5 | E8: 5 | F8: =INDEX(C8:E8,MATCH($B$4,$C$6:$E$6,0))
A9: Operating days per year | B9: days | C9: 365 | D9: 365 | E9: 365 | F9: =INDEX(C9:E9,MATCH($B$4,$C$6:$E$6,0))
A10: Occupancy — year 1 (2025) | B10: % of available rooms | C10: 0.65 | D10: 0.7 | E10: 0.55 | F10: =INDEX(C10:E10,MATCH($B$4,$C$6:$E$6,0))
A11: Occupancy — year 2 (2026) | B11: % of available rooms | C11: 0.7 | D11: 0.75 | E11: 0.6 | F11: =INDEX(C11:E11,MATCH($B$4,$C$6:$E$6,0))
A12: Occupancy — year 3 (2027) | B12: % of available rooms | C12: 0.75 | D12: 0.8 | E12: 0.65 | F12: =INDEX(C12:E12,MATCH($B$4,$C$6:$E$6,0))
A13: Occupancy — year 4 (2028) and after (stabilised) | B13: % of available rooms | C13: 0.8 | D13: 0.85 | E13: 0.7 | F13: =INDEX(C13:E13,MATCH($B$4,$C$6:$E$6,0))
A14: ADR — year 1 (2025) | B14: € per occupied room | C14: 113.2207 | D14: 124.54 | E14: 101.9 | F14: =INDEX(C14:E14,MATCH($B$4,$C$6:$E$6,0))
A15: ADR — year 2 (2026) | B15: € per occupied room | C15: 121.9006 | D15: 134.09 | E15: 109.71 | F15: =INDEX(C15:E15,MATCH($B$4,$C$6:$E$6,0))
A16: ADR — year 3 (2027) | B16: € per occupied room | C16: 130.8829 | D16: 143.97 | E16: 117.79 | F16: =INDEX(C16:E16,MATCH($B$4,$C$6:$E$6,0))
A17: ADR — year 4 (2028) (stabilised level) | B17: € per occupied room | C17: 140.5027 | D17: 154.55 | E17: 126.45 | F17: =INDEX(C17:E17,MATCH($B$4,$C$6:$E$6,0))
A18: Annual growth after stabilisation (inflation) | B18: % per year, from year 5 (2029) | C18: 0.02 | D18: 0.025 | E18: 0.015 | F18: =INDEX(C18:E18,MATCH($B$4,$C$6:$E$6,0))
A19: FOOD & BEVERAGE (all-day bar/restaurant)
A20: F&B revenue — year 1 (2025) | B20: € per year | C20: 1045493 | D20: 1202317 | E20: 836394 | F20: =INDEX(C20:E20,MATCH($B$4,$C$6:$E$6,0))
A21: F&B revenue — year 2 (2026) | B21: € per year | C21: 1332401 | D21: 1532261 | E21: 1065921 | F21: =INDEX(C21:E21,MATCH($B$4,$C$6:$E$6,0))
A22: F&B revenue — year 3 (2027) | B22: € per year | C22: 1598479 | D22: 1838251 | E22: 1278783 | F22: =INDEX(C22:E22,MATCH($B$4,$C$6:$E$6,0))
A23: F&B revenue — year 4 (2028) (stabilised level) | B23: € per year | C23: 1811423 | D23: 2083136 | E23: 1449138 | F23: =INDEX(C23:E23,MATCH($B$4,$C$6:$E$6,0))
A24: DEPARTMENTAL COSTS
A25: Rooms dept. cost — year 1 | B25: % of room revenue | C25: 0.122845 | D25: 0.122845 | E25: 0.122845 | F25: =INDEX(C25:E25,MATCH($B$4,$C$6:$E$6,0))
A26: Rooms dept. cost — year 2 | B26: % of room revenue | C26: 0.119645 | D26: 0.119645 | E26: 0.119645 | F26: =INDEX(C26:E26,MATCH($B$4,$C$6:$E$6,0))
A27: Rooms dept. cost — year 3 | B27: % of room revenue | C27: 0.11676 | D27: 0.11676 | E27: 0.11676 | F27: =INDEX(C27:E27,MATCH($B$4,$C$6:$E$6,0))
A28: Rooms dept. cost — year 4 and after | B28: % of room revenue | C28: 0.114023 | D28: 0.114023 | E28: 0.114023 | F28: =INDEX(C28:E28,MATCH($B$4,$C$6:$E$6,0))
A29: F&B dept. cost | B29: % of F&B revenue | C29: 0.375 | D29: 0.36 | E29: 0.4 | F29: =INDEX(C29:E29,MATCH($B$4,$C$6:$E$6,0))
A30: Staff cost — year 1 (32 FTEs, all departments) | B30: € per year, grows with inflation | C30: 533868 | D30: 533868 | E30: 560561 | F30: =INDEX(C30:E30,MATCH($B$4,$C$6:$E$6,0))
A31: UNDISTRIBUTED OPERATING EXPENSES
A32: Administrative & general — fixed part, year 1 | B32: € per year, grows with inflation | C32: 82211.98 | D32: 82211.98 | E32: 82211.98 | F32: =INDEX(C32:E32,MATCH($B$4,$C$6:$E$6,0))
A33: Administrative & general — variable part | B33: % of total revenue | C33: 0.02 | D33: 0.02 | E33: 0.02 | F33: =INDEX(C33:E33,MATCH($B$4,$C$6:$E$6,0))
A34: Marketing | B34: % of total revenue | C34: 0.03 | D34: 0.03 | E34: 0.03 | F34: =INDEX(C34:E34,MATCH($B$4,$C$6:$E$6,0))
A35: Property operations & maintenance | B35: % of total revenue | C35: 0.03 | D35: 0.03 | E35: 0.03 | F35: =INDEX(C35:E35,MATCH($B$4,$C$6:$E$6,0))
A36: Utility costs | B36: % of total revenue | C36: 0.045 | D36: 0.045 | E36: 0.045 | F36: =INDEX(C36:E36,MATCH($B$4,$C$6:$E$6,0))
A37: FIXED CHARGES
A38: Annual rent — tier 1 (from 2024) | B38: € per year | C38: 15000 | D38: 15000 | E38: 15000 | F38: =INDEX(C38:E38,MATCH($B$4,$C$6:$E$6,0))
A39: Rent tier 2 starts in | B39: year | C39: 2030 | D39: 2030 | E39: 2030 | F39: =INDEX(C39:E39,MATCH($B$4,$C$6:$E$6,0))
A40: Annual rent — tier 2 | B40: € per year | C40: 21000 | D40: 21000 | E40: 21000 | F40: =INDEX(C40:E40,MATCH($B$4,$C$6:$E$6,0))
A41: Rent tier 3 starts in | B41: year | C41: 2035 | D41: 2035 | E41: 2035 | F41: =INDEX(C41:E41,MATCH($B$4,$C$6:$E$6,0))
A42: Annual rent — tier 3 (implied by the PDF's 2044 NOI and NPV) | B42: € per year | C42: 90000 | D42: 90000 | E42: 90000 | F42: =INDEX(C42:E42,MATCH($B$4,$C$6:$E$6,0))
A43: Reserve for replacement — year 1 | B43: % of total revenue | C43: 0.01 | D43: 0.01 | E43: 0.01 | F43: =INDEX(C43:E43,MATCH($B$4,$C$6:$E$6,0))
A44: Reserve for replacement — year 2 onwards | B44: % of total revenue | C44: 0.02 | D44: 0.02 | E44: 0.02 | F44: =INDEX(C44:E44,MATCH($B$4,$C$6:$E$6,0))
A45: INVESTMENT & RETURNS
A46: CAPEX (excl. VAT) | B46: € | C46: 1500000 | D46: 1400000 | E46: 1800000 | F46: =INDEX(C46:E46,MATCH($B$4,$C$6:$E$6,0))
A47: Pre-opening expenses (excl. VAT) | B47: € | C47: 100000 | D47: 100000 | E47: 100000 | F47: =INDEX(C47:E47,MATCH($B$4,$C$6:$E$6,0))
A48: VAT rate on CAPEX & pre-opening | B48: % | C48: 0.24 | D48: 0.24 | E48: 0.24 | F48: =INDEX(C48:E48,MATCH($B$4,$C$6:$E$6,0))
A49: CAPEX grant (% of CAPEX excl. VAT, received 2025) | B49: plan mentions applying for 60-75% | C49: 0 | D49: 0.6 | E49: 0 | F49: =INDEX(C49:E49,MATCH($B$4,$C$6:$E$6,0))
A50: Discount rate for NPV | B50: % per year | C50: 0.1 | D50: 0.1 | E50: 0.1 | F50: =INDEX(C50:E50,MATCH($B$4,$C$6:$E$6,0))

Sheet Model
A1: Operating model — P&L forecast (nominal €)
A2: All cells are formulas driven by the Inputs sheet. Years 1-4 (2025-2028) are the ramp-up; from year 5 revenue and cost lines grow at the inflation input. Layout mirrors pages 9-10 of the PDF, extended to 2044 for the returns calculation.
A3: Year | B3: 2025 | C3: 2026 | D3: 2027 | E3: 2028 | F3: 2029 | G3: 2030 | H3: 2031 | I3: 2032 | J3: 2033 | K3: 2034 | L3: 2035 | M3: 2036 | N3: 2037 | O3: 2038 | P3: 2039 | Q3: 2040 | R3: 2041 | S3: 2042 | T3: 2043 | U3: 2044
A4: ACCOMMODATION — KEY INDICATORS
A5: Number of rooms | B5: =Inputs!$F$8 | C5: =Inputs!$F$8 | D5: =Inputs!$F$8 | E5: =Inputs!$F$8 | F5: =Inputs!$F$8 | G5: =Inputs!$F$8 | H5: =Inputs!$F$8 | I5: =Inputs!$F$8 | ... U5: =Inputs!$F$8
A6: Operating days | B6: =Inputs!$F$9 | C6: =Inputs!$F$9 | D6: =Inputs!$F$9 | E6: =Inputs!$F$9 | F6: =Inputs!$F$9 | G6: =Inputs!$F$9 | H6: =Inputs!$F$9 | I6: =Inputs!$F$9 | ... U6: =Inputs!$F$9
A7: Available room nights | B7: =B5*B6 | C7: =C5*C6 | D7: =D5*D6 | E7: =E5*E6 | F7: =F5*F6 | G7: =G5*G6 | H7: =H5*H6 | I7: =I5*I6 | ... U7: =U5*U6
A8: Occupancy | B8: =Inputs!$F$10 | C8: =Inputs!$F$11 | D8: =Inputs!$F$12 | E8: =Inputs!$F$13 | F8: =Inputs!$F$13 | G8: =Inputs!$F$13 | H8: =Inputs!$F$13 | I8: =Inputs!$F$13 | J8: =Inputs!$F$13 | K8: =Inputs!$F$13 | L8: =Inputs!$F$13 | ... U8: =Inputs!$F$13
A9: Occupied room nights | B9: =B7*B8 | C9: =C7*C8 | D9: =D7*D8 | E9: =E7*E8 | F9: =F7*F8 | G9: =G7*G8 | H9: =H7*H8 | I9: =I7*I8 | ... U9: =U7*U8
A10: ADR | B10: =Inputs!$F$14 | C10: =Inputs!$F$15 | D10: =Inputs!$F$16 | E10: =Inputs!$F$17 | F10: =E10*(1+Inputs!$F$18) | G10: =F10*(1+Inputs!$F$18) | H10: =G10*(1+Inputs!$F$18) | I10: =H10*(1+Inputs!$F$18) | J10: =I10*(1+Inputs!$F$18) | K10: =J10*(1+Inputs!$F$18) | L10: =K10*(1+Inputs!$F$18) | M10: =L10*(1+Inputs!$F$18) | ... U10: =T10*(1+Inputs!$F$18)
A11: RevPAR | B11: =B8*B10 | C11: =C8*C10 | D11: =D8*D10 | E11: =E8*E10 | F11: =F8*F10 | G11: =G8*G10 | H11: =H8*H10 | I11: =I8*I10 | ... U11: =U8*U10
A12: REVENUE
A13: Room revenue | B13: =B9*B10 | C13: =C9*C10 | D13: =D9*D10 | E13: =E9*E10 | F13: =F9*F10 | G13: =G9*G10 | H13: =H9*H10 | I13: =I9*I10 | ... U13: =U9*U10
A14: Food & Beverages (all-day bar/restaurant) | B14: =Inputs!$F$20 | C14: =Inputs!$F$21 | D14: =Inputs!$F$22 | E14: =Inputs!$F$23 | F14: =E14*(1+Inputs!$F$18) | G14: =F14*(1+Inputs!$F$18) | H14: =G14*(1+Inputs!$F$18) | I14: =H14*(1+Inputs!$F$18) | J14: =I14*(1+Inputs!$F$18) | K14: =J14*(1+Inputs!$F$18) | L14: =K14*(1+Inputs!$F$18) | M14: =L14*(1+Inputs!$F$18) | ... U14: =T14*(1+Inputs!$F$18)
A15: Total revenue | B15: =B13+B14 | C15: =C13+C14 | D15: =D13+D14 | E15: =E13+E14 | F15: =F13+F14 | G15: =G13+G14 | H15: =H13+H14 | I15: =I13+I14 | ... U15: =U13+U14
A16: DEPARTMENTAL EXPENSES
A17: Rooms | B17: =B13*Inputs!$F$25 | C17: =C13*Inputs!$F$26 | D17: =D13*Inputs!$F$27 | E17: =E13*Inputs!$F$28 | F17: =F13*Inputs!$F$28 | G17: =G13*Inputs!$F$28 | H17: =H13*Inputs!$F$28 | I17: =I13*Inputs!$F$28 | J17: =J13*Inputs!$F$28 | K17: =K13*Inputs!$F$28 | L17: =L13*Inputs!$F$28 | ... U17: =U13*Inputs!$F$28
A18: Food & Beverage | B18: =B14*Inputs!$F$29 | C18: =C14*Inputs!$F$29 | D18: =D14*Inputs!$F$29 | E18: =E14*Inputs!$F$29 | F18: =F14*Inputs!$F$29 | G18: =G14*Inputs!$F$29 | H18: =H14*Inputs!$F$29 | I18: =I14*Inputs!$F$29 | ... U18: =U14*Inputs!$F$29
A19: Staff | B19: =Inputs!$F$30 | C19: =B19*(1+Inputs!$F$18) | D19: =C19*(1+Inputs!$F$18) | E19: =D19*(1+Inputs!$F$18) | F19: =E19*(1+Inputs!$F$18) | G19: =F19*(1+Inputs!$F$18) | H19: =G19*(1+Inputs!$F$18) | I19: =H19*(1+Inputs!$F$18) | J19: =I19*(1+Inputs!$F$18) | ... U19: =T19*(1+Inputs!$F$18)
A20: Total departmental expenses | B20: =SUM(B17:B19) | C20: =SUM(C17:C19) | D20: =SUM(D17:D19) | E20: =SUM(E17:E19) | F20: =SUM(F17:F19) | G20: =SUM(G17:G19) | H20: =SUM(H17:H19) | I20: =SUM(I17:I19) | ... U20: =SUM(U17:U19)
A21: Percentage of revenue | B21: =B20/B15 | C21: =C20/C15 | D21: =D20/D15 | E21: =E20/E15 | F21: =F20/F15 | G21: =G20/G15 | H21: =H20/H15 | I21: =I20/I15 | ... U21: =U20/U15
A22: DEPARTMENTAL INCOME (LOSS) | B22: =B15-B20 | C22: =C15-C20 | D22: =D15-D20 | E22: =E15-E20 | F22: =F15-F20 | G22: =G15-G20 | H22: =H15-H20 | I22: =I15-I20 | ... U22: =U15-U20
A23: Percentage of revenue | B23: =B22/B15 | C23: =C22/C15 | D23: =D22/D15 | E23: =E22/E15 | F23: =F22/F15 | G23: =G22/G15 | H23: =H22/H15 | I23: =I22/I15 | ... U23: =U22/U15
A24: UNDISTRIBUTED OPERATING EXPENSES
A25: Administrative and General | B25: =Inputs!$F$32*POWER(1+Inputs!$F$18,0)+Inputs!$F$33*B15 | C25: =Inputs!$F$32*POWER(1+Inputs!$F$18,1)+Inputs!$F$33*C15 | D25: =Inputs!$F$32*POWER(1+Inputs!$F$18,2)+Inputs!$F$33*D15 | E25: =Inputs!$F$32*POWER(1+Inputs!$F$18,3)+Inputs!$F$33*E15 | F25: =Inputs!$F$32*POWER(1+Inputs!$F$18,4)+Inputs!$F$33*F15 | G25: =Inputs!$F$32*POWER(1+Inputs!$F$18,5)+Inputs!$F$33*G15 | H25: =Inputs!$F$32*POWER(1+Inputs!$F$18,6)+Inputs!$F$33*H15 | I25: =Inputs!$F$32*POWER(1+Inputs!$F$18,7)+Inputs!$F$33*I15 | J25: =Inputs!$F$32*POWER(1+Inputs!$F$18,8)+Inputs!$F$33*J15 | K25: =Inputs!$F$32*POWER(1+Inputs!$F$18,9)+Inputs!$F$33*K15 | L25: =Inputs!$F$32*POWER(1+Inputs!$F$18,10)+Inputs!$F$33*L15 | M25: =Inputs!$F$32*POWER(1+Inputs!$F$18,11)+Inputs!$F$33*M15 | N25: =Inputs!$F$32*POWER(1+Inputs!$F$18,12)+Inputs!$F$33*N15 | O25: =Inputs!$F$32*POWER(1+Inputs!$F$18,13)+Inputs!$F$33*O15 | P25: =Inputs!$F$32*POWER(1+Inputs!$F$18,14)+Inputs!$F$33*P15 | Q25: =Inputs!$F$32*POWER(1+Inputs!$F$18,15)+Inputs!$F$33*Q15 | R25: =Inputs!$F$32*POWER(1+Inputs!$F$18,16)+Inputs!$F$33*R15 | S25: =Inputs!$F$32*POWER(1+Inputs!$F$18,17)+Inputs!$F$33*S15 | T25: =Inputs!$F$32*POWER(1+Inputs!$F$18,18)+Inputs!$F$33*T15 | U25: =Inputs!$F$32*POWER(1+Inputs!$F$18,19)+Inputs!$F$33*U15
A26: Marketing | B26: =Inputs!$F$34*B15 | C26: =Inputs!$F$34*C15 | D26: =Inputs!$F$34*D15 | E26: =Inputs!$F$34*E15 | F26: =Inputs!$F$34*F15 | G26: =Inputs!$F$34*G15 | H26: =Inputs!$F$34*H15 | I26: =Inputs!$F$34*I15 | ... U26: =Inputs!$F$34*U15
A27: Property Operations and Maintenance | B27: =Inputs!$F$35*B15 | C27: =Inputs!$F$35*C15 | D27: =Inputs!$F$35*D15 | E27: =Inputs!$F$35*E15 | F27: =Inputs!$F$35*F15 | G27: =Inputs!$F$35*G15 | H27: =Inputs!$F$35*H15 | I27: =Inputs!$F$35*I15 | ... U27: =Inputs!$F$35*U15
A28: Utility Costs | B28: =Inputs!$F$36*B15 | C28: =Inputs!$F$36*C15 | D28: =Inputs!$F$36*D15 | E28: =Inputs!$F$36*E15 | F28: =Inputs!$F$36*F15 | G28: =Inputs!$F$36*G15 | H28: =Inputs!$F$36*H15 | I28: =Inputs!$F$36*I15 | ... U28: =Inputs!$F$36*U15
A29: Total undistributed expenses | B29: =SUM(B25:B28) | C29: =SUM(C25:C28) | D29: =SUM(D25:D28) | E29: =SUM(E25:E28) | F29: =SUM(F25:F28) | G29: =SUM(G25:G28) | H29: =SUM(H25:H28) | I29: =SUM(I25:I28) | ... U29: =SUM(U25:U28)
A30: Percentage of revenue | B30: =B29/B15 | C30: =C29/C15 | D30: =D29/D15 | E30: =E29/E15 | F30: =F29/F15 | G30: =G29/G15 | H30: =H29/H15 | I30: =I29/I15 | ... U30: =U29/U15
A31: EBITDAR | B31: =B22-B29 | C31: =C22-C29 | D31: =D22-D29 | E31: =E22-E29 | F31: =F22-F29 | G31: =G22-G29 | H31: =H22-H29 | I31: =I22-I29 | ... U31: =U22-U29
A32: Percentage of revenue | B32: =B31/B15 | C32: =C31/C15 | D32: =D31/D15 | E32: =E31/E15 | F32: =F31/F15 | G32: =G31/G15 | H32: =H31/H15 | I32: =I31/I15 | ... U32: =U31/U15
A33: Rent | B33: =IF(B3>=Inputs!$F$41,Inputs!$F$42,IF(B3>=Inputs!$F$39,Inputs!$F$40,Inputs!$F$38)) | C33: =IF(C3>=Inputs!$F$41,Inputs!$F$42,IF(C3>=Inputs!$F$39,Inputs!$F$40,Inputs!$F$38)) | D33: =IF(D3>=Inputs!$F$41,Inputs!$F$42,IF(D3>=Inputs!$F$39,Inputs!$F$40,Inputs!$F$38)) | E33: =IF(E3>=Inputs!$F$41,Inputs!$F$42,IF(E3>=Inputs!$F$39,Inputs!$F$40,Inputs!$F$38)) | F33: =IF(F3>=Inputs!$F$41,Inputs!$F$42,IF(F3>=Inputs!$F$39,Inputs!$F$40,Inputs!$F$38)) | G33: =IF(G3>=Inputs!$F$41,Inputs!$F$42,IF(G3>=Inputs!$F$39,Inputs!$F$40,Inputs!$F$38)) | H33: =IF(H3>=Inputs!$F$41,Inputs!$F$42,IF(H3>=Inputs!$F$39,Inputs!$F$40,Inputs!$F$38)) | I33: =IF(I3>=Inputs!$F$41,Inputs!$F$42,IF(I3>=Inputs!$F$39,Inputs!$F$40,Inputs!$F$38)) | ... U33: =IF(U3>=Inputs!$F$41,Inputs!$F$42,IF(U3>=Inputs!$F$39,Inputs!$F$40,Inputs!$F$38))
A34: EBITDA | B34: =B31-B33 | C34: =C31-C33 | D34: =D31-D33 | E34: =E31-E33 | F34: =F31-F33 | G34: =G31-G33 | H34: =H31-H33 | I34: =I31-I33 | ... U34: =U31-U33
A35: Reserve for replacement | B35: =Inputs!$F$43*B15 | C35: =Inputs!$F$44*C15 | D35: =Inputs!$F$44*D15 | E35: =Inputs!$F$44*E15 | F35: =Inputs!$F$44*F15 | G35: =Inputs!$F$44*G15 | H35: =Inputs!$F$44*H15 | I35: =Inputs!$F$44*I15 | J35: =Inputs!$F$44*J15 | ... U35: =Inputs!$F$44*U15
A36: NET OPERATING INCOME | B36: =B34-B35 | C36: =C34-C35 | D36: =D34-D35 | E36: =E34-E35 | F36: =F34-F35 | G36: =G34-G35 | H36: =H34-H35 | I36: =I34-I35 | ... U36: =U34-U35
A37: Percentage of revenue | B37: =B36/B15 | C37: =C36/C15 | D37: =D36/D15 | E37: =E36/E15 | F37: =F36/F15 | G37: =G36/G15 | H37: =H36/H15 | I37: =I36/I15 | ... U37: =U36/U15

Sheet Returns
A1: Unlevered returns (nominal €)
A2: 2024: rent during works plus CAPEX incl. VAT. 2025: first operating year plus full VAT recovery (per the plan). NPV uses Excel's NPV() over 2024-2044, i.e. the 2024 outflow is discounted by one year — this is the convention the PDF's €746,821 was computed with.
A3: Year | B3: 2024 | C3: 2025 | D3: 2026 | E3: 2027 | F3: 2028 | G3: 2029 | H3: 2030 | I3: 2031 | J3: 2032 | K3: 2033 | L3: 2034 | M3: 2035 | N3: 2036 | O3: 2037 | P3: 2038 | Q3: 2039 | R3: 2040 | S3: 2041 | T3: 2042 | U3: 2043 | V3: 2044
A4: NOI | B4: =-IF(B3>=Inputs!$F$41,Inputs!$F$42,IF(B3>=Inputs!$F$39,Inputs!$F$40,Inputs!$F$38)) | C4: =Model!B36 | D4: =Model!C36 | E4: =Model!D36 | F4: =Model!E36 | G4: =Model!F36 | H4: =Model!G36 | I4: =Model!H36 | J4: =Model!I36 | ... V4: =Model!U36
A5: CAPEX incl. VAT | B5: =-(Inputs!$F$46+Inputs!$F$47)*(1+Inputs!$F$48)
A6: CAPEX VAT recovery | C6: =(Inputs!$F$46+Inputs!$F$47)*Inputs!$F$48
A7: CAPEX grant (if any) | C7: =Inputs!$F$49*Inputs!$F$46
A8: Net cash flow | B8: =SUM(B4:B7) | C8: =SUM(C4:C7) | D8: =SUM(D4:D7) | E8: =SUM(E4:E7) | F8: =SUM(F4:F7) | G8: =SUM(G4:G7) | H8: =SUM(H4:H7) | I8: =SUM(I4:I7) | ... V8: =SUM(V4:V7)
A10: NPV @ discount rate | B10: =NPV(Inputs!$F$50,B8:V8)
A11: IRR (unlevered) | B11: =IRR(B8:V8)

Sheet Check vs PDF
A1: Accuracy check — live model vs the printed PDF figures
A2: =IF(Inputs!$B$4<>"Base","SWITCH THE SCENARIO TO Base — these checks compare the Base scenario to the PDF","Comparing Base scenario to the PDF. Tolerances allow for the PDF's own rounding (it prints whole euros / one decimal).")
A4: Checks passed: | B4: =COUNTIF(H7:H234,"OK")&" of "&COUNTA(H7:H234)
A6: Statement | B6: Line item | C6: Year | D6: PDF value | E6: Model value | F6: Difference | G6: Tolerance | H6: Status
A7: KPIs (p.9) | B7: Occupancy | C7: 2025 | D7: 0.65 | E7: =Model!B8 | F7: =E7-D7 | G7: 0.005 | H7: =IF(ABS(F7)<=G7,"OK","CHECK")
A8: KPIs (p.9) | B8: Occupancy | C8: 2026 | D8: 0.7 | E8: =Model!C8 | F8: =E8-D8 | G8: 0.005 | H8: =IF(ABS(F8)<=G8,"OK","CHECK")
A9: KPIs (p.9) | B9: Occupancy | C9: 2027 | D9: 0.75 | E9: =Model!D8 | F9: =E9-D9 | G9: 0.005 | H9: =IF(ABS(F9)<=G9,"OK","CHECK")
A10: KPIs (p.9) | B10: Occupancy | C10: 2028 | D10: 0.8 | E10: =Model!E8 | F10: =E10-D10 | G10: 0.005 | H10: =IF(ABS(F10)<=G10,"OK","CHECK")
A11: KPIs (p.9) | B11: Occupancy | C11: 2029 | D11: 0.8 | E11: =Model!F8 | F11: =E11-D11 | G11: 0.005 | H11: =IF(ABS(F11)<=G11,"OK","CHECK")
A12: KPIs (p.9) | B12: Occupancy | C12: 2030 | D12: 0.8 | E12: =Model!G8 | F12: =E12-D12 | G12: 0.005 | H12: =IF(ABS(F12)<=G12,"OK","CHECK")
A13: KPIs (p.9) | B13: Occupancy | C13: 2031 | D13: 0.8 | E13: =Model!H8 | F13: =E13-D13 | G13: 0.005 | H13: =IF(ABS(F13)<=G13,"OK","CHECK")
A14: KPIs (p.9) | B14: Occupancy | C14: 2032 | D14: 0.8 | E14: =Model!I8 | F14: =E14-D14 | G14: 0.005 | H14: =IF(ABS(F14)<=G14,"OK","CHECK")
A15: KPIs (p.9) | B15: Occupancy | C15: 2033 | D15: 0.8 | E15: =Model!J8 | F15: =E15-D15 | G15: 0.005 | H15: =IF(ABS(F15)<=G15,"OK","CHECK")
A16: KPIs (p.9) | B16: Occupancy | C16: 2034 | D16: 0.8 | E16: =Model!K8 | F16: =E16-D16 | G16: 0.005 | H16: =IF(ABS(F16)<=G16,"OK","CHECK")
A17: KPIs (p.9) | B17: Occupied room nights | C17: 2025 | D17: 1186 | E17: =Model!B9 | F17: =E17-D17 | G17: 1 | H17: =IF(ABS(F17)<=G17,"OK","CHECK")
A18: KPIs (p.9) | B18: Occupied room nights | C18: 2026 | D18: 1278 | E18: =Model!C9 | F18: =E18-D18 | G18: 1 | H18: =IF(ABS(F18)<=G18,"OK","CHECK")
A19: KPIs (p.9) | B19: Occupied room nights | C19: 2027 | D19: 1369 | E19: =Model!D9 | F19: =E19-D19 | G19: 1 | H19: =IF(ABS(F19)<=G19,"OK","CHECK")
A20: KPIs (p.9) | B20: Occupied room nights | C20: 2028 | D20: 1460 | E20: =Model!E9 | F20: =E20-D20 | G20: 1 | H20: =IF(ABS(F20)<=G20,"OK","CHECK")
A21: KPIs (p.9) | B21: Occupied room nights | C21: 2029 | D21: 1460 | E21: =Model!F9 | F21: =E21-D21 | G21: 1 | H21: =IF(ABS(F21)<=G21,"OK","CHECK")
A22: KPIs (p.9) | B22: Occupied room nights | C22: 2030 | D22: 1460 | E22: =Model!G9 | F22: =E22-D22 | G22: 1 | H22: =IF(ABS(F22)<=G22,"OK","CHECK")
A23: KPIs (p.9) | B23: Occupied room nights | C23: 2031 | D23: 1460 | E23: =Model!H9 | F23: =E23-D23 | G23: 1 | H23: =IF(ABS(F23)<=G23,"OK","CHECK")
A24: KPIs (p.9) | B24: Occupied room nights | C24: 2032 | D24: 1460 | E24: =Model!I9 | F24: =E24-D24 | G24: 1 | H24: =IF(ABS(F24)<=G24,"OK","CHECK")
A25: KPIs (p.9) | B25: Occupied room nights | C25: 2033 | D25: 1460 | E25: =Model!J9 | F25: =E25-D25 | G25: 1 | H25: =IF(ABS(F25)<=G25,"OK","CHECK")
A26: KPIs (p.9) | B26: Occupied room nights | C26: 2034 | D26: 1460 | E26: =Model!K9 | F26: =E26-D26 | G26: 1 | H26: =IF(ABS(F26)<=G26,"OK","CHECK")
A27: KPIs (p.9) | B27: ADR | C27: 2025 | D27: 113 | E27: =Model!B10 | F27: =E27-D27 | G27: 0.51 | H27: =IF(ABS(F27)<=G27,"OK","CHECK")
A28: KPIs (p.9) | B28: ADR | C28: 2026 | D28: 122 | E28: =Model!C10 | F28: =E28-D28 | G28: 0.51 | H28: =IF(ABS(F28)<=G28,"OK","CHECK")
A29: KPIs (p.9) | B29: ADR | C29: 2027 | D29: 131 | E29: =Model!D10 | F29: =E29-D29 | G29: 0.51 | H29: =IF(ABS(F29)<=G29,"OK","CHECK")
A30: KPIs (p.9) | B30: ADR | C30: 2028 | D30: 141 | E30: =Model!E10 | F30: =E30-D30 | G30: 0.51 | H30: =IF(ABS(F30)<=G30,"OK","CHECK")
A31: KPIs (p.9) | B31: ADR | C31: 2029 | D31: 143 | E31: =Model!F10 | F31: =E31-D31 | G31: 0.51 | H31: =IF(ABS(F31)<=G31,"OK","CHECK")
A32: KPIs (p.9) | B32: ADR | C32: 2030 | D32: 146 | E32: =Model!G10 | F32: =E32-D32 | G32: 0.51 | H32: =IF(ABS(F32)<=G32,"OK","CHECK")
A33: KPIs (p.9) | B33: ADR | C33: 2031 | D33: 149 | E33: =Model!H10 | F33: =E33-D33 | G33: 0.51 | H33: =IF(ABS(F33)<=G33,"OK","CHECK")
A34: KPIs (p.9) | B34: ADR | C34: 2032 | D34: 152 | E34: =Model!I10 | F34: =E34-D34 | G34: 0.51 | H34: =IF(ABS(F34)<=G34,"OK","CHECK")
A35: KPIs (p.9) | B35: ADR | C35: 2033 | D35: 155 | E35: =Model!J10 | F35: =E35-D35 | G35: 0.51 | H35: =IF(ABS(F35)<=G35,"OK","CHECK")
A36: KPIs (p.9) | B36: ADR | C36: 2034 | D36: 158 | E36: =Model!K10 | F36: =E36-D36 | G36: 0.51 | H36: =IF(ABS(F36)<=G36,"OK","CHECK")
A37: KPIs (p.9) | B37: RevPAR | C37: 2025 | D37: 74 | E37: =Model!B11 | F37: =E37-D37 | G37: 0.51 | H37: =IF(ABS(F37)<=G37,"OK","CHECK")
A38: KPIs (p.9) | B38: RevPAR | C38: 2026 | D38: 85 | E38: =Model!C11 | F38: =E38-D38 | G38: 0.51 | H38: =IF(ABS(F38)<=G38,"OK","CHECK")
A39: KPIs (p.9) | B39: RevPAR | C39: 2027 | D39: 98 | E39: =Model!D11 | F39: =E39-D39 | G39: 0.51 | H39: =IF(ABS(F39)<=G39,"OK","CHECK")
A40: KPIs (p.9) | B40: RevPAR | C40: 2028 | D40: 112 | E40: =Model!E11 | F40: =E40-D40 | G40: 0.51 | H40: =IF(ABS(F40)<=G40,"OK","CHECK")
A41: KPIs (p.9) | B41: RevPAR | C41: 2029 | D41: 115 | E41: =Model!F11 | F41: =E41-D41 | G41: 0.51 | H41: =IF(ABS(F41)<=G41,"OK","CHECK")
A42: KPIs (p.9) | B42: RevPAR | C42: 2030 | D42: 117 | E42: =Model!G11 | F42: =E42-D42 | G42: 0.51 | H42: =IF(ABS(F42)<=G42,"OK","CHECK")
A43: KPIs (p.9) | B43: RevPAR | C43: 2031 | D43: 119 | E43: =Model!H11 | F43: =E43-D43 | G43: 0.51 | H43: =IF(ABS(F43)<=G43,"OK","CHECK")
A44: KPIs (p.9) | B44: RevPAR | C44: 2032 | D44: 122 | E44: =Model!I11 | F44: =E44-D44 | G44: 0.51 | H44: =IF(ABS(F44)<=G44,"OK","CHECK")
A45: KPIs (p.9) | B45: RevPAR | C45: 2033 | D45: 124 | E45: =Model!J11 | F45: =E45-D45 | G45: 0.51 | H45: =IF(ABS(F45)<=G45,"OK","CHECK")
A46: KPIs (p.9) | B46: RevPAR | C46: 2034 | D46: 127 | E46: =Model!K11 | F46: =E46-D46 | G46: 0.51 | H46: =IF(ABS(F46)<=G46,"OK","CHECK")
A47: P&L (p.10) | B47: Room revenue | C47: 2025 | D47: 134308 | E47: =Model!B13 | F47: =E47-D47 | G47: 2 | H47: =IF(ABS(F47)<=G47,"OK","CHECK")
A48: P&L (p.10) | B48: Room revenue | C48: 2026 | D48: 155728 | E48: =Model!C13 | F48: =E48-D48 | G48: 2 | H48: =IF(ABS(F48)<=G48,"OK","CHECK")
A49: P&L (p.10) | B49: Room revenue | C49: 2027 | D49: 179146 | E49: =Model!D13 | F49: =E49-D49 | G49: 2 | H49: =IF(ABS(F49)<=G49,"OK","CHECK")
A50: P&L (p.10) | B50: Room revenue | C50: 2028 | D50: 205134 | E50: =Model!E13 | F50: =E50-D50 | G50: 2 | H50: =IF(ABS(F50)<=G50,"OK","CHECK")
A51: P&L (p.10) | B51: Room revenue | C51: 2029 | D51: 209237 | E51: =Model!F13 | F51: =E51-D51 | G51: 2 | H51: =IF(ABS(F51)<=G51,"OK","CHECK")
A52: P&L (p.10) | B52: Room revenue | C52: 2030 | D52: 213422 | E52: =Model!G13 | F52: =E52-D52 | G52: 2 | H52: =IF(ABS(F52)<=G52,"OK","CHECK")
A53: P&L (p.10) | B53: Room revenue | C53: 2031 | D53: 217690 | E53: =Model!H13 | F53: =E53-D53 | G53: 2 | H53: =IF(ABS(F53)<=G53,"OK","CHECK")
A54: P&L (p.10) | B54: Room revenue | C54: 2032 | D54: 222044 | E54: =Model!I13 | F54: =E54-D54 | G54: 2 | H54: =IF(ABS(F54)<=G54,"OK","CHECK")
A55: P&L (p.10) | B55: Room revenue | C55: 2033 | D55: 226485 | E55: =Model!J13 | F55: =E55-D55 | G55: 2 | H55: =IF(ABS(F55)<=G55,"OK","CHECK")
A56: P&L (p.10) | B56: Room revenue | C56: 2034 | D56: 231015 | E56: =Model!K13 | F56: =E56-D56 | G56: 2 | H56: =IF(ABS(F56)<=G56,"OK","CHECK")
A57: P&L (p.10) | B57: Food & Beverages | C57: 2025 | D57: 1045493 | E57: =Model!B14 | F57: =E57-D57 | G57: 2 | H57: =IF(ABS(F57)<=G57,"OK","CHECK")
A58: P&L (p.10) | B58: Food & Beverages | C58: 2026 | D58: 1332401 | E58: =Model!C14 | F58: =E58-D58 | G58: 2 | H58: =IF(ABS(F58)<=G58,"OK","CHECK")
A59: P&L (p.10) | B59: Food & Beverages | C59: 2027 | D59: 1598479 | E59: =Model!D14 | F59: =E59-D59 | G59: 2 | H59: =IF(ABS(F59)<=G59,"OK","CHECK")
A60: P&L (p.10) | B60: Food & Beverages | C60: 2028 | D60: 1811423 | E60: =Model!E14 | F60: =E60-D60 | G60: 2 | H60: =IF(ABS(F60)<=G60,"OK","CHECK")
A61: P&L (p.10) | B61: Food & Beverages | C61: 2029 | D61: 1847652 | E61: =Model!F14 | F61: =E61-D61 | G61: 2 | H61: =IF(ABS(F61)<=G61,"OK","CHECK")
A62: P&L (p.10) | B62: Food & Beverages | C62: 2030 | D62: 1884605 | E62: =Model!G14 | F62: =E62-D62 | G62: 2 | H62: =IF(ABS(F62)<=G62,"OK","CHECK")
A63: P&L (p.10) | B63: Food & Beverages | C63: 2031 | D63: 1922297 | E63: =Model!H14 | F63: =E63-D63 | G63: 2 | H63: =IF(ABS(F63)<=G63,"OK","CHECK")
A64: P&L (p.10) | B64: Food & Beverages | C64: 2032 | D64: 1960743 | E64: =Model!I14 | F64: =E64-D64 | G64: 2 | H64: =IF(ABS(F64)<=G64,"OK","CHECK")
A65: P&L (p.10) | B65: Food & Beverages | C65: 2033 | D65: 1999958 | E65: =Model!J14 | F65: =E65-D65 | G65: 2 | H65: =IF(ABS(F65)<=G65,"OK","CHECK")
A66: P&L (p.10) | B66: Food & Beverages | C66: 2034 | D66: 2039957 | E66: =Model!K14 | F66: =E66-D66 | G66: 2 | H66: =IF(ABS(F66)<=G66,"OK","CHECK")
A67: P&L (p.10) | B67: Total revenue | C67: 2025 | D67: 1179801 | E67: =Model!B15 | F67: =E67-D67 | G67: 2 | H67: =IF(ABS(F67)<=G67,"OK","CHECK")
A68: P&L (p.10) | B68: Total revenue | C68: 2026 | D68: 1488129 | E68: =Model!C15 | F68: =E68-D68 | G68: 2 | H68: =IF(ABS(F68)<=G68,"OK","CHECK")
A69: P&L (p.10) | B69: Total revenue | C69: 2027 | D69: 1777626 | E69: =Model!D15 | F69: =E69-D69 | G69: 2 | H69: =IF(ABS(F69)<=G69,"OK","CHECK")
A70: P&L (p.10) | B70: Total revenue | C70: 2028 | D70: 2016558 | E70: =Model!E15 | F70: =E70-D70 | G70: 2 | H70: =IF(ABS(F70)<=G70,"OK","CHECK")
A71: P&L (p.10) | B71: Total revenue | C71: 2029 | D71: 2056889 | E71: =Model!F15 | F71: =E71-D71 | G71: 2 | H71: =IF(ABS(F71)<=G71,"OK","CHECK")
A72: P&L (p.10) | B72: Total revenue | C72: 2030 | D72: 2098027 | E72: =Model!G15 | F72: =E72-D72 | G72: 2 | H72: =IF(ABS(F72)<=G72,"OK","CHECK")
A73: P&L (p.10) | B73: Total revenue | C73: 2031 | D73: 2139987 | E73: =Model!H15 | F73: =E73-D73 | G73: 2 | H73: =IF(ABS(F73)<=G73,"OK","CHECK")
A74: P&L (p.10) | B74: Total revenue | C74: 2032 | D74: 2182787 | E74: =Model!I15 | F74: =E74-D74 | G74: 2 | H74: =IF(ABS(F74)<=G74,"OK","CHECK")
A75: P&L (p.10) | B75: Total revenue | C75: 2033 | D75: 2226443 | E75: =Model!J15 | F75: =E75-D75 | G75: 2 | H75: =IF(ABS(F75)<=G75,"OK","CHECK")
A76: P&L (p.10) | B76: Total revenue | C76: 2034 | D76: 2270972 | E76: =Model!K15 | F76: =E76-D76 | G76: 2 | H76: =IF(ABS(F76)<=G76,"OK","CHECK")
A77: P&L (p.10) | B77: Rooms expense | C77: 2025 | D77: 16499 | E77: =Model!B17 | F77: =E77-D77 | G77: 2 | H77: =IF(ABS(F77)<=G77,"OK","CHECK")
A78: P&L (p.10) | B78: Rooms expense | C78: 2026 | D78: 18632 | E78: =Model!C17 | F78: =E78-D78 | G78: 2 | H78: =IF(ABS(F78)<=G78,"OK","CHECK")
A79: P&L (p.10) | B79: Rooms expense | C79: 2027 | D79: 20917 | E79: =Model!D17 | F79: =E79-D79 | G79: 2 | H79: =IF(ABS(F79)<=G79,"OK","CHECK")
A80: P&L (p.10) | B80: Rooms expense | C80: 2028 | D80: 23390 | E80: =Model!E17 | F80: =E80-D80 | G80: 2 | H80: =IF(ABS(F80)<=G80,"OK","CHECK")
A81: P&L (p.10) | B81: Rooms expense | C81: 2029 | D81: 23858 | E81: =Model!F17 | F81: =E81-D81 | G81: 2 | H81: =IF(ABS(F81)<=G81,"OK","CHECK")
A82: P&L (p.10) | B82: Rooms expense | C82: 2030 | D82: 24335 | E82: =Model!G17 | F82: =E82-D82 | G82: 2 | H82: =IF(ABS(F82)<=G82,"OK","CHECK")
A83: P&L (p.10) | B83: Rooms expense | C83: 2031 | D83: 24822 | E83: =Model!H17 | F83: =E83-D83 | G83: 2 | H83: =IF(ABS(F83)<=G83,"OK","CHECK")
A84: P&L (p.10) | B84: Rooms expense | C84: 2032 | D84: 25319 | E84: =Model!I17 | F84: =E84-D84 | G84: 2 | H84: =IF(ABS(F84)<=G84,"OK","CHECK")
A85: P&L (p.10) | B85: Rooms expense | C85: 2033 | D85: 25825 | E85: =Model!J17 | F85: =E85-D85 | G85: 2 | H85: =IF(ABS(F85)<=G85,"OK","CHECK")
A86: P&L (p.10) | B86: Rooms expense | C86: 2034 | D86: 26341 | E86: =Model!K17 | F86: =E86-D86 | G86: 2 | H86: =IF(ABS(F86)<=G86,"OK","CHECK")
A87: P&L (p.10) | B87: F&B expense | C87: 2025 | D87: 392060 | E87: =Model!B18 | F87: =E87-D87 | G87: 2 | H87: =IF(ABS(F87)<=G87,"OK","CHECK")
A88: P&L (p.10) | B88: F&B expense | C88: 2026 | D88: 499650 | E88: =Model!C18 | F88: =E88-D88 | G88: 2 | H88: =IF(ABS(F88)<=G88,"OK","CHECK")
A89: P&L (p.10) | B89: F&B expense | C89: 2027 | D89: 599430 | E89: =Model!D18 | F89: =E89-D89 | G89: 2 | H89: =IF(ABS(F89)<=G89,"OK","CHECK")
A90: P&L (p.10) | B90: F&B expense | C90: 2028 | D90: 679284 | E90: =Model!E18 | F90: =E90-D90 | G90: 2 | H90: =IF(ABS(F90)<=G90,"OK","CHECK")
A91: P&L (p.10) | B91: F&B expense | C91: 2029 | D91: 692869 | E91: =Model!F18 | F91: =E91-D91 | G91: 2 | H91: =IF(ABS(F91)<=G91,"OK","CHECK")
A92: P&L (p.10) | B92: F&B expense | C92: 2030 | D92: 706727 | E92: =Model!G18 | F92: =E92-D92 | G92: 2 | H92: =IF(ABS(F92)<=G92,"OK","CHECK")
A93: P&L (p.10) | B93: F&B expense | C93: 2031 | D93: 720861 | E93: =Model!H18 | F93: =E93-D93 | G93: 2 | H93: =IF(ABS(F93)<=G93,"OK","CHECK")
A94: P&L (p.10) | B94: F&B expense | C94: 2032 | D94: 735279 | E94: =Model!I18 | F94: =E94-D94 | G94: 2 | H94: =IF(ABS(F94)<=G94,"OK","CHECK")
A95: P&L (p.10) | B95: F&B expense | C95: 2033 | D95: 749984 | E95: =Model!J18 | F95: =E95-D95 | G95: 2 | H95: =IF(ABS(F95)<=G95,"OK","CHECK")
A96: P&L (p.10) | B96: F&B expense | C96: 2034 | D96: 764984 | E96: =Model!K18 | F96: =E96-D96 | G96: 2 | H96: =IF(ABS(F96)<=G96,"OK","CHECK")
A97: P&L (p.10) | B97: Staff | C97: 2025 | D97: 533868 | E97: =Model!B19 | F97: =E97-D97 | G97: 2 | H97: =IF(ABS(F97)<=G97,"OK","CHECK")
A98: P&L (p.10) | B98: Staff | C98: 2026 | D98: 544545 | E98: =Model!C19 | F98: =E98-D98 | G98: 2 | H98: =IF(ABS(F98)<=G98,"OK","CHECK")
A99: P&L (p.10) | B99: Staff | C99: 2027 | D99: 555436 | E99: =Model!D19 | F99: =E99-D99 | G99: 2 | H99: =IF(ABS(F99)<=G99,"OK","CHECK")
A100: P&L (p.10) | B100: Staff | C100: 2028 | D100: 566545 | E100: =Model!E19 | F100: =E100-D100 | G100: 2 | H100: =IF(ABS(F100)<=G100,"OK","CHECK")
A101: P&L (p.10) | B101: Staff | C101: 2029 | D101: 577876 | E101: =Model!F19 | F101: =E101-D101 | G101: 2 | H101: =IF(ABS(F101)<=G101,"OK","CHECK")
A102: P&L (p.10) | B102: Staff | C102: 2030 | D102: 589433 | E102: =Model!G19 | F102: =E102-D102 | G102: 2 | H102: =IF(ABS(F102)<=G102,"OK","CHECK")
...
